time_measure/__init__.py
time_measure/main.py
time_measure/test.py
time_measure-0.1.1.dist-info/LICENSE
time_measure-0.1.1.dist-info/METADATA
time_measure-0.1.1.dist-info/WHEEL
time_measure-0.1.1.dist-info/top_level.txt
time_measure-0.1.1.dist-info/RECORD
