Metadata-Version: 2.1
Name: time-measure
Version: 0.1.1
Summary: Various tools to easily measure elapsed time in python (with function wrapper, context manager, or decorator).
Home-page: https://github.com/ThibaultCastells/time_measure
Author: Thibault Castells
Author-email: thib.castells@icloud.com
Classifier: Programming Language :: Python :: 3
Classifier: License :: OSI Approved :: MIT License
Classifier: Operating System :: OS Independent
License-File: LICENSE
